{
	"info": {
		"_postman_id": "2267ea97-ff54-4215-a131-c1f1d3daa564",
		"name": "final assign",
		"schema": "https://schema.getpostman.com/json/collection/v2.0.0/collection.json",
		"_exporter_id": "42715712"
	},
	"item": [
		{
			"name": "update profile",
			"request": {
				"method": "GET",
				"header": []
			},
			"response": []
		},
		{
			"name": "add new category",
			"request": {
				"method": "GET",
				"header": []
			},
			"response": []
		},
		{
			"name": "blog post",
			"request": {
				"method": "GET",
				"header": []
			},
			"response": []
		},
		{
			"name": "login user",
			"request": {
				"method": "GET",
				"header": []
			},
			"response": []
		},
		{
			"name": "register user",
			"request": {
				"method": "GET",
				"header": []
			},
			"response": []
		},
		{
			"name": "list-post-by-category",
			"request": {
				"method": "GET",
				"header": []
			},
			"response": []
		},
		{
			"name": "Update post",
			"request": {
				"method": "GET",
				"header": []
			},
			"response": []
		},
		{
			"name": "like unlike post",
			"request": {
				"method": "GET",
				"header": []
			},
			"response": []
		},
		{
			"name": "/posts-by-likes",
			"request": {
				"method": "GET",
				"header": []
			},
			"response": []
		}
	]
}